overboard/__init__.py
overboard/__main__.py
overboard/experiments.py
overboard/fastslider.py
overboard/flowlayout.py
overboard/overboard_gui.py
overboard/pg_time_axis.py
overboard/plots.py
overboard/plotwidget.py
overboard/style.qss
overboard/tshow.py
overboard/visualizations.py
overboard/window.py
overboard-1.0.1.dist-info/LICENSE
overboard-1.0.1.dist-info/METADATA
overboard-1.0.1.dist-info/WHEEL
overboard-1.0.1.dist-info/top_level.txt
overboard-1.0.1.dist-info/RECORD
