Metadata-Version: 2.1
Name: overboard
Version: 1.0.1
Summary: Pure Python dashboard for monitoring deep learning experiments
Home-page: https://github.com/jotaf98/overboard
Author: Joao Henriques
License: UNKNOWN
Platform: UNKNOWN
Classifier: Programming Language :: Python :: 3
Classifier: License :: OSI Approved :: GNU General Public License v3 (GPLv3)
Classifier: Operating System :: OS Independent
Requires-Python: >=3.6
License-File: LICENSE
Requires-Dist: pyqt5 (>=5.12)
Requires-Dist: pyqtgraph (<0.12,>=0.11)
Requires-Dist: pyopengl (>=3.1)
Requires-Dist: fs (>=2.4)
Requires-Dist: overboard-logger (>=0.7.1)
